assemblyline_ui/VERSION
assemblyline_ui/__init__.py
assemblyline_ui/app.py
assemblyline_ui/config.py
assemblyline_ui/error.py
assemblyline_ui/gunicorn_config.py
assemblyline_ui/gunicorn_config_socketio.py
assemblyline_ui/healthz.py
assemblyline_ui/http_exceptions.py
assemblyline_ui/logger.py
assemblyline_ui/patched.py
assemblyline_ui/socketsrv.py
assemblyline_ui/api/__init__.py
assemblyline_ui/api/base.py
assemblyline_ui/api/v4/__init__.py
assemblyline_ui/api/v4/alert.py
assemblyline_ui/api/v4/apikey.py
assemblyline_ui/api/v4/archive.py
assemblyline_ui/api/v4/assistant.py
assemblyline_ui/api/v4/authentication.py
assemblyline_ui/api/v4/badlist.py
assemblyline_ui/api/v4/bundle.py
assemblyline_ui/api/v4/error.py
assemblyline_ui/api/v4/federated_lookup.py
assemblyline_ui/api/v4/file.py
assemblyline_ui/api/v4/hash_search.py
assemblyline_ui/api/v4/help.py
assemblyline_ui/api/v4/heuristics.py
assemblyline_ui/api/v4/ingest.py
assemblyline_ui/api/v4/live.py
assemblyline_ui/api/v4/ontology.py
assemblyline_ui/api/v4/proxy.py
assemblyline_ui/api/v4/replay.py
assemblyline_ui/api/v4/result.py
assemblyline_ui/api/v4/retrohunt.py
assemblyline_ui/api/v4/safelist.py
assemblyline_ui/api/v4/search.py
assemblyline_ui/api/v4/service.py
assemblyline_ui/api/v4/signature.py
assemblyline_ui/api/v4/submission.py
assemblyline_ui/api/v4/submit.py
assemblyline_ui/api/v4/system.py
assemblyline_ui/api/v4/ui.py
assemblyline_ui/api/v4/user.py
assemblyline_ui/api/v4/webauthn.py
assemblyline_ui/api/v4/workflow.py
assemblyline_ui/helper/__init__.py
assemblyline_ui/helper/discover.py
assemblyline_ui/helper/oauth.py
assemblyline_ui/helper/result.py
assemblyline_ui/helper/search.py
assemblyline_ui/helper/service.py
assemblyline_ui/helper/signature.py
assemblyline_ui/helper/submission.py
assemblyline_ui/helper/user.py
assemblyline_ui/helper/ai/__init__.py
assemblyline_ui/helper/ai/base.py
assemblyline_ui/helper/ai/cohere.py
assemblyline_ui/helper/ai/openai.py
assemblyline_ui/security/__init__.py
assemblyline_ui-4.7.0.1.dist-info/licenses/LICENCE.md
assemblyline_ui-4.7.0.1.dist-info/METADATA
assemblyline_ui-4.7.0.1.dist-info/WHEEL
assemblyline_ui-4.7.0.1.dist-info/top_level.txt
assemblyline_ui-4.7.0.1.dist-info/RECORD
