Metadata-Version: 2.4
Name: assemblyline-ui
Version: 4.7.0.1
Summary: Assemblyline 4 - API and Socket IO server
Home-page: https://github.com/CybercentreCanada/assemblyline-ui/
Author: CCCS Assemblyline development team
Author-email: assemblyline@cyber.gc.ca
License: MIT
Keywords: assemblyline automated malware analysis gc canada cse-cst cse cst cyber cccs
Classifier: Development Status :: 5 - Production/Stable
Classifier: Intended Audience :: Developers
Classifier: Topic :: Software Development :: Libraries
Classifier: License :: OSI Approved :: MIT License
Classifier: Programming Language :: Python :: 3.7
Classifier: Programming Language :: Python :: 3.8
Classifier: Programming Language :: Python :: 3.9
Classifier: Programming Language :: Python :: 3.10
Classifier: Programming Language :: Python :: 3.11
License-File: LICENCE.md
Requires-Dist: assemblyline
Requires-Dist: assemblyline-core
Requires-Dist: werkzeug
Requires-Dist: flask<3.0.0
Requires-Dist: pyqrcode
Requires-Dist: markdown
Requires-Dist: python-ldap
Requires-Dist: python3-saml
Requires-Dist: Authlib>=1.3.1
Requires-Dist: fido2<1.0.0
Requires-Dist: PyJWT
Requires-Dist: gunicorn
Requires-Dist: gevent
Requires-Dist: xmlsec==1.3.14
Requires-Dist: lxml==5.3.2
Provides-Extra: test
Requires-Dist: pytest; extra == "test"
Requires-Dist: pytest-mock; extra == "test"
Requires-Dist: cart; extra == "test"
Provides-Extra: socketio
Requires-Dist: python-socketio; extra == "socketio"
Requires-Dist: flask-socketio; extra == "socketio"
Requires-Dist: gevent-websocket; extra == "socketio"
Dynamic: author
Dynamic: author-email
Dynamic: classifier
Dynamic: description
Dynamic: description-content-type
Dynamic: home-page
Dynamic: keywords
Dynamic: license
Dynamic: license-file
Dynamic: provides-extra
Dynamic: requires-dist
Dynamic: summary
